singctl/__init__.py
singctl/bin/nssm.exe
singctl/bin/sing-box.exe
singctl/exceptions.py
singctl/main.py
singctl/utils.py
singctl-0.3.1.dist-info/WHEEL
singctl-0.3.1.dist-info/entry_points.txt
singctl-0.3.1.dist-info/METADATA
singctl-0.3.1.dist-info/RECORD
