Metadata-Version: 2.3
Name: singctl
Version: 0.3.1
Author: pixelcola
Author-email: pixelcola <swakpo@outlook.com>
Requires-Dist: httpx>=0.28.1
Requires-Dist: tinydb>=4.8.2
Requires-Dist: typer>=0.19.2
Requires-Python: >=3.12
